Metadata-Version: 1.1
Name: iva
Version: 1.0.3
Summary: Iterative Virus Assembler
Home-page: https://github.com/sanger-pathogens/iva
Author: Martin Hunt
Author-email: path-help@sanger.ac.uk
License: GPLv3
Platform: UNKNOWN
Classifier: Development Status :: 4 - Beta
Classifier: Topic :: Scientific/Engineering :: Bio-Informatics
Classifier: Programming Language :: Python :: 3 :: Only
Classifier: License :: OSI Approved :: GNU General Public License v3 (GPLv3)
